{"startTime":"","endTime":"","essIndex":12,"goal":"cylinder","sssIndex":0,"start":"enter","taskType":"competition","points":[{"name":"WP-1","lat":-17.70319,"lng":-149.076,"alt":0,"radius":400},{"name":"WP-2","lat":-17.92415,"lng":-149.05952,"alt":0,"radius":400},{"name":"WP-3","lat":-18.10829,"lng":-149.26277,"alt":0,"radius":400},{"name":"WP-4","lat":-18.14027,"lng":-149.73656,"alt":0,"radius":400},{"name":"WP-5","lat":-17.84411,"lng":-150.7449,"alt":0,"radius":400},{"name":"WP-6","lat":-17.03344,"lng":-151.89056,"alt":0,"radius":400},{"name":"WP-7","lat":-16.74731,"lng":-152.19785,"alt":0,"radius":400},{"name":"WP-8","lat":-16.51457,"lng":-152.37482,"alt":0,"radius":400},{"name":"WP-9","lat":-16.34613,"lng":-152.34444,"alt":0,"radius":400},{"name":"WP-10","lat":-16.13245,"lng":-152.1011,"alt":0,"radius":400},{"name":"WP-11","lat":-16.09938,"lng":-151.74104,"alt":0,"radius":400},{"name":"WP-12","lat":-16.8814,"lng":-149.49109,"alt":0,"radius":400},{"name":"WP-8","lat":-17.70319,"lng":-149.07584,"alt":0,"radius":400}]}